ship_langchain/__init__.py
ship_langchain/callbacks.py
ship_langchain/chains.py
ship_langchain/py.typed
ship_langchain/tools.py
ship_langchain-0.1.0b2.dist-info/METADATA
ship_langchain-0.1.0b2.dist-info/WHEEL
ship_langchain-0.1.0b2.dist-info/licenses/LICENSE
ship_langchain-0.1.0b2.dist-info/RECORD
