Metadata-Version: 2.4
Name: ship-langchain
Version: 0.1.0b2
Summary: LangChain integration for SHIP Protocol - AI coding reliability metrics
Project-URL: Homepage, https://vibeatlas.dev
Project-URL: Documentation, https://vibeatlas.dev/docs/ship/langchain
Project-URL: Repository, https://github.com/vibeatlas/ship-protocol
Project-URL: Changelog, https://github.com/vibeatlas/ship-protocol/releases
Author-email: VibeAtlas <team@vibeatlas.dev>
License-Expression: MIT
License-File: LICENSE
Keywords: agents,ai,coding,langchain,metrics,reliability,ship,tools
Classifier: Development Status :: 4 - Beta
Classifier: Intended Audience :: Developers
Classifier: License :: OSI Approved :: MIT License
Classifier: Operating System :: OS Independent
Classifier: Programming Language :: Python :: 3
Classifier: Programming Language :: Python :: 3.9
Classifier: Programming Language :: Python :: 3.10
Classifier: Programming Language :: Python :: 3.11
Classifier: Programming Language :: Python :: 3.12
Classifier: Topic :: Scientific/Engineering :: Artificial Intelligence
Classifier: Topic :: Software Development :: Libraries :: Python Modules
Requires-Python: >=3.9
Requires-Dist: langchain-core>=0.1.0
Requires-Dist: vibeatlas-ship>=0.1.0b0
Provides-Extra: dev
Requires-Dist: mypy>=1.0.0; extra == 'dev'
Requires-Dist: pytest-asyncio>=0.21.0; extra == 'dev'
Requires-Dist: pytest>=7.0.0; extra == 'dev'
Requires-Dist: ruff>=0.1.0; extra == 'dev'
